odoo/addons/sms_ovh_http/README.rst
odoo/addons/sms_ovh_http/__init__.py
odoo/addons/sms_ovh_http/__manifest__.py
odoo/addons/sms_ovh_http/i18n/es.po
odoo/addons/sms_ovh_http/i18n/it.po
odoo/addons/sms_ovh_http/i18n/sms_ovh_http.pot
odoo/addons/sms_ovh_http/models/__init__.py
odoo/addons/sms_ovh_http/models/iap_account.py
odoo/addons/sms_ovh_http/models/sms_api.py
odoo/addons/sms_ovh_http/models/sms_sms.py
odoo/addons/sms_ovh_http/readme/CONFIGURE.rst
odoo/addons/sms_ovh_http/readme/CONTRIBUTORS.rst
odoo/addons/sms_ovh_http/readme/DESCRIPTION.rst
odoo/addons/sms_ovh_http/static/description/icon.png
odoo/addons/sms_ovh_http/static/description/index.html
odoo/addons/sms_ovh_http/static/img/img.png
odoo/addons/sms_ovh_http/static/img/img_1.png
odoo/addons/sms_ovh_http/static/img/img_2.png
odoo/addons/sms_ovh_http/tests/__init__.py
odoo/addons/sms_ovh_http/tests/test_send_sms.py
odoo/addons/sms_ovh_http/views/iap_account_view.xml
odoo/addons/sms_ovh_http/views/sms_sms_view.xml
odoo_addon_sms_ovh_http-16.0.1.0.0.4.dist-info/METADATA
odoo_addon_sms_ovh_http-16.0.1.0.0.4.dist-info/WHEEL
odoo_addon_sms_ovh_http-16.0.1.0.0.4.dist-info/top_level.txt
odoo_addon_sms_ovh_http-16.0.1.0.0.4.dist-info/RECORD
