Metadata-Version: 2.1
Name: odoo-addon-sms_ovh_http
Version: 16.0.1.0.0.4
Summary: Send sms using ovh http API
Home-page: https://github.com/OCA/connector-telephony
Author: Akretion, Odoo Community Association (OCA)
Author-email: support@odoo-community.org
License: AGPL-3
Classifier: Programming Language :: Python
Classifier: Framework :: Odoo
Classifier: Framework :: Odoo :: 16.0
Classifier: License :: OSI Approved :: GNU Affero General Public License v3
Requires-Python: >=3.10
Requires-Dist: odoo-addon-base-phone<16.1dev,>=16.0dev
Requires-Dist: odoo-addon-iap-alternative-provider<16.1dev,>=16.0dev
Requires-Dist: odoo<16.1dev,>=16.0a
